encoder_interface/__init__.py
encoder_interface/__main__.py
encoder_interface/encoder_interface.py
encoder_interface/serial_interface.py
encoder_interface1_0_0-1.0.0.dist-info/WHEEL
encoder_interface1_0_0-1.0.0.dist-info/METADATA
encoder_interface1_0_0-1.0.0.dist-info/RECORD
