Metadata-Version: 2.1
Name: encoder-interface1-0-0
Version: 1.0.0
Summary: 
Author: MartinP96
Author-email: porenta.martin@gmail.com
Requires-Python: >=3.10,<4.0
Classifier: Programming Language :: Python :: 3
Classifier: Programming Language :: Python :: 3.10
Classifier: Programming Language :: Python :: 3.11
Requires-Dist: pyserial (>=3.5,<4.0)
